[
  {
    "inputs": [
      {
        "internalType": "contract IxNUGG",
        "name": "_xnugg",
        "type": "address"
      }
    ],
    "stateMutability": "nonpayable",
    "type": "constructor"
  },
  {
    "anonymous": false,
    "inputs": [
      {
        "indexed": false,
        "internalType": "uint128",
        "name": "interval",
        "type": "uint128"
      },
      {
        "indexed": false,
        "internalType": "uint128",
        "name": "baseblock",
        "type": "uint128"
      }
    ],
    "name": "Genesis",
    "type": "event"
  },
  {
    "anonymous": false,
    "inputs": [
      {
        "indexed": false,
        "internalType": "address",
        "name": "nft",
        "type": "address"
      },
      {
        "indexed": false,
        "internalType": "uint256",
        "name": "tokenid",
        "type": "uint256"
      },
      {
        "indexed": false,
        "internalType": "uint256",
        "name": "swapnum",
        "type": "uint256"
      },
      {
        "indexed": false,
        "internalType": "address",
        "name": "account",
        "type": "address"
      }
    ],
    "name": "SubmitClaim",
    "type": "event"
  },
  {
    "anonymous": false,
    "inputs": [
      {
        "indexed": false,
        "internalType": "address",
        "name": "nft",
        "type": "address"
      },
      {
        "indexed": false,
        "internalType": "uint256",
        "name": "tokenid",
        "type": "uint256"
      },
      {
        "indexed": false,
        "internalType": "uint256",
        "name": "swapnum",
        "type": "uint256"
      },
      {
        "indexed": false,
        "internalType": "address",
        "name": "account",
        "type": "address"
      },
      {
        "indexed": false,
        "internalType": "uint256",
        "name": "amount",
        "type": "uint256"
      }
    ],
    "name": "SubmitOffer",
    "type": "event"
  },
  {
    "anonymous": false,
    "inputs": [
      {
        "indexed": false,
        "internalType": "address",
        "name": "nft",
        "type": "address"
      },
      {
        "indexed": false,
        "internalType": "uint256",
        "name": "tokenid",
        "type": "uint256"
      },
      {
        "indexed": false,
        "internalType": "uint256",
        "name": "swapnum",
        "type": "uint256"
      },
      {
        "indexed": false,
        "internalType": "address",
        "name": "account",
        "type": "address"
      },
      {
        "indexed": false,
        "internalType": "uint256",
        "name": "amount",
        "type": "uint256"
      },
      {
        "indexed": false,
        "internalType": "uint64",
        "name": "epoch",
        "type": "uint64"
      }
    ],
    "name": "SubmitSwap",
    "type": "event"
  },
  {
    "inputs": [
      {
        "internalType": "uint64",
        "name": "id",
        "type": "uint64"
      }
    ],
    "name": "blocknumFromId",
    "outputs": [
      {
        "internalType": "uint256",
        "name": "",
        "type": "uint256"
      }
    ],
    "stateMutability": "view",
    "type": "function"
  },
  {
    "inputs": [],
    "name": "currentEpochId",
    "outputs": [
      {
        "internalType": "uint64",
        "name": "res",
        "type": "uint64"
      }
    ],
    "stateMutability": "view",
    "type": "function"
  },
  {
    "inputs": [],
    "name": "currentSeed",
    "outputs": [
      {
        "internalType": "bytes32",
        "name": "res",
        "type": "bytes32"
      }
    ],
    "stateMutability": "view",
    "type": "function"
  },
  {
    "inputs": [
      {
        "internalType": "uint256",
        "name": "blocknum",
        "type": "uint256"
      }
    ],
    "name": "epochFromBlocknum",
    "outputs": [
      {
        "components": [
          {
            "internalType": "uint64",
            "name": "id",
            "type": "uint64"
          },
          {
            "internalType": "uint256",
            "name": "startblock",
            "type": "uint256"
          },
          {
            "internalType": "uint256",
            "name": "endblock",
            "type": "uint256"
          },
          {
            "internalType": "enum EpochMath.Status",
            "name": "status",
            "type": "uint8"
          }
        ],
        "internalType": "struct EpochMath.Epoch",
        "name": "res",
        "type": "tuple"
      }
    ],
    "stateMutability": "view",
    "type": "function"
  },
  {
    "inputs": [
      {
        "internalType": "uint64",
        "name": "id",
        "type": "uint64"
      }
    ],
    "name": "epochFromId",
    "outputs": [
      {
        "components": [
          {
            "internalType": "uint64",
            "name": "id",
            "type": "uint64"
          },
          {
            "internalType": "uint256",
            "name": "startblock",
            "type": "uint256"
          },
          {
            "internalType": "uint256",
            "name": "endblock",
            "type": "uint256"
          },
          {
            "internalType": "enum EpochMath.Status",
            "name": "status",
            "type": "uint8"
          }
        ],
        "internalType": "struct EpochMath.Epoch",
        "name": "res",
        "type": "tuple"
      }
    ],
    "stateMutability": "view",
    "type": "function"
  },
  {
    "inputs": [
      {
        "internalType": "uint64",
        "name": "id",
        "type": "uint64"
      }
    ],
    "name": "epochStatus",
    "outputs": [
      {
        "internalType": "enum EpochMath.Status",
        "name": "res",
        "type": "uint8"
      }
    ],
    "stateMutability": "view",
    "type": "function"
  },
  {
    "inputs": [],
    "name": "genesisBlock",
    "outputs": [
      {
        "internalType": "uint256",
        "name": "res",
        "type": "uint256"
      }
    ],
    "stateMutability": "view",
    "type": "function"
  },
  {
    "inputs": [
      {
        "internalType": "uint256",
        "name": "id",
        "type": "uint256"
      }
    ],
    "name": "getSeed",
    "outputs": [
      {
        "internalType": "bytes32",
        "name": "res",
        "type": "bytes32"
      }
    ],
    "stateMutability": "view",
    "type": "function"
  },
  {
    "inputs": [
      {
        "internalType": "uint256",
        "name": "id",
        "type": "uint256"
      },
      {
        "internalType": "uint256",
        "name": "offset",
        "type": "uint256"
      }
    ],
    "name": "getSeedWithOffset",
    "outputs": [
      {
        "internalType": "bytes32",
        "name": "res",
        "type": "bytes32"
      }
    ],
    "stateMutability": "view",
    "type": "function"
  },
  {
    "inputs": [],
    "name": "interval",
    "outputs": [
      {
        "internalType": "uint256",
        "name": "res",
        "type": "uint256"
      }
    ],
    "stateMutability": "view",
    "type": "function"
  },
  {
    "inputs": [],
    "name": "nuggGet",
    "outputs": [],
    "stateMutability": "nonpayable",
    "type": "function"
  },
  {
    "inputs": [],
    "name": "nuggSet",
    "outputs": [],
    "stateMutability": "nonpayable",
    "type": "function"
  },
  {
    "inputs": [
      {
        "internalType": "address",
        "name": "",
        "type": "address"
      },
      {
        "internalType": "address",
        "name": "",
        "type": "address"
      },
      {
        "internalType": "uint256",
        "name": "",
        "type": "uint256"
      },
      {
        "internalType": "bytes",
        "name": "",
        "type": "bytes"
      }
    ],
    "name": "onERC721Received",
    "outputs": [
      {
        "internalType": "bytes4",
        "name": "",
        "type": "bytes4"
      }
    ],
    "stateMutability": "nonpayable",
    "type": "function"
  },
  {
    "inputs": [
      {
        "internalType": "uint256",
        "name": "id",
        "type": "uint256"
      }
    ],
    "name": "seedExists",
    "outputs": [
      {
        "internalType": "bool",
        "name": "res",
        "type": "bool"
      }
    ],
    "stateMutability": "view",
    "type": "function"
  },
  {
    "inputs": [
      {
        "internalType": "address",
        "name": "nft",
        "type": "address"
      },
      {
        "internalType": "uint256",
        "name": "tokenid",
        "type": "uint256"
      },
      {
        "internalType": "uint256",
        "name": "swapnum",
        "type": "uint256"
      }
    ],
    "name": "submitClaim",
    "outputs": [],
    "stateMutability": "nonpayable",
    "type": "function"
  },
  {
    "inputs": [
      {
        "internalType": "address",
        "name": "nft",
        "type": "address"
      },
      {
        "internalType": "uint256",
        "name": "tokenid",
        "type": "uint256"
      },
      {
        "internalType": "uint256",
        "name": "swapnum",
        "type": "uint256"
      }
    ],
    "name": "submitOffer",
    "outputs": [],
    "stateMutability": "payable",
    "type": "function"
  },
  {
    "inputs": [
      {
        "internalType": "address",
        "name": "nft",
        "type": "address"
      },
      {
        "internalType": "uint256",
        "name": "tokenid",
        "type": "uint256"
      },
      {
        "internalType": "uint64",
        "name": "requestedEpoch",
        "type": "uint64"
      },
      {
        "internalType": "uint128",
        "name": "requestedFloor",
        "type": "uint128"
      }
    ],
    "name": "submitSwap",
    "outputs": [],
    "stateMutability": "nonpayable",
    "type": "function"
  },
  {
    "inputs": [],
    "name": "xnugg",
    "outputs": [
      {
        "internalType": "contract IxNUGG",
        "name": "",
        "type": "address"
      }
    ],
    "stateMutability": "view",
    "type": "function"
  }
]